secure_id.py
secureid-1.0.1.dist-info/METADATA
secureid-1.0.1.dist-info/WHEEL
secureid-1.0.1.dist-info/top_level.txt
secureid-1.0.1.dist-info/RECORD
